Metadata-Version: 2.1
Name: mondigy
Version: 1.0.2
Summary: A small wrapper for connecting MongoDB collections to Prodigy
Home-page: https://github.com/jdagdelen/mondigy
Author: John Dagdelen
Author-email: jdagdelen@berkeley.edu
License: UNKNOWN
Project-URL: Bug Tracker, https://github.com/jdagdelen/mondigy/issues
Platform: UNKNOWN
Classifier: Programming Language :: Python :: 3
Classifier: License :: OSI Approved :: MIT License
Classifier: Operating System :: OS Independent
Requires-Python: >=3.6
